{
"meta":{"test_sets":[],"test_metrics":[],"learn_metrics":[{"best_value":"Min","name":"Logloss"}],"launch_mode":"Train","parameters":"","iteration_count":100,"learn_sets":["learn"],"name":"experiment"},
"iterations":[
{"learn":[0.6881885539],"iteration":0,"passed_time":0.06338889918,"remaining_time":6.275501019},
{"learn":[0.6836014539],"iteration":1,"passed_time":0.1244889711,"remaining_time":6.099959583},
{"learn":[0.679594183],"iteration":2,"passed_time":0.1850352313,"remaining_time":5.982805812},
{"learn":[0.6759946537],"iteration":3,"passed_time":0.2428730973,"remaining_time":5.828954335},
{"learn":[0.6726984591],"iteration":4,"passed_time":0.3078476012,"remaining_time":5.849104423},
{"learn":[0.6698924344],"iteration":5,"passed_time":0.3626447526,"remaining_time":5.681434458},
{"learn":[0.6673824241],"iteration":6,"passed_time":0.4256215429,"remaining_time":5.654686213},
{"learn":[0.665219709],"iteration":7,"passed_time":0.4878560288,"remaining_time":5.610344332},
{"learn":[0.6633134167],"iteration":8,"passed_time":0.5454377382,"remaining_time":5.514981575},
{"learn":[0.6616142359],"iteration":9,"passed_time":0.6046221349,"remaining_time":5.441599214},
{"learn":[0.6601017942],"iteration":10,"passed_time":0.6629848554,"remaining_time":5.364150194},
{"learn":[0.6587934821],"iteration":11,"passed_time":0.7170548269,"remaining_time":5.258402064},
{"learn":[0.6574732959],"iteration":12,"passed_time":0.7804228519,"remaining_time":5.222829855},
{"learn":[0.6563600167],"iteration":13,"passed_time":0.8388499449,"remaining_time":5.152935376},
{"learn":[0.6554345555],"iteration":14,"passed_time":0.8927786302,"remaining_time":5.059078904},
{"learn":[0.6545921003],"iteration":15,"passed_time":0.947020345,"remaining_time":4.971856811},
{"learn":[0.6538733097],"iteration":16,"passed_time":1.000656667,"remaining_time":4.88555902},
{"learn":[0.6533065433],"iteration":17,"passed_time":1.066769293,"remaining_time":4.859726779},
{"learn":[0.6526545242],"iteration":18,"passed_time":1.123201047,"remaining_time":4.788383411},
{"learn":[0.6520455779],"iteration":19,"passed_time":1.186677818,"remaining_time":4.746711271},
{"learn":[0.6514707678],"iteration":20,"passed_time":1.249860308,"remaining_time":4.701855446},
{"learn":[0.650966406],"iteration":21,"passed_time":1.312474488,"remaining_time":4.653318639},
{"learn":[0.6504817022],"iteration":22,"passed_time":1.368549256,"remaining_time":4.581664901},
{"learn":[0.6501871165],"iteration":23,"passed_time":1.423851179,"remaining_time":4.508862068},
{"learn":[0.6498221357],"iteration":24,"passed_time":1.488456364,"remaining_time":4.465369093},
{"learn":[0.6494853854],"iteration":25,"passed_time":1.552099337,"remaining_time":4.417513498},
{"learn":[0.6490678232],"iteration":26,"passed_time":1.609108652,"remaining_time":4.350553022},
{"learn":[0.6488632132],"iteration":27,"passed_time":1.665744065,"remaining_time":4.283341881},
{"learn":[0.6485678205],"iteration":28,"passed_time":1.723808505,"remaining_time":4.220358755},
{"learn":[0.6483234884],"iteration":29,"passed_time":1.776856934,"remaining_time":4.145999512},
{"learn":[0.6480719156],"iteration":30,"passed_time":1.83627028,"remaining_time":4.087182235},
{"learn":[0.6479137959],"iteration":31,"passed_time":1.89624977,"remaining_time":4.029530762},
{"learn":[0.6477689624],"iteration":32,"passed_time":1.953467786,"remaining_time":3.966131565},
{"learn":[0.6476145719],"iteration":33,"passed_time":2.00545813,"remaining_time":3.892948135},
{"learn":[0.6474089503],"iteration":34,"passed_time":2.064961639,"remaining_time":3.834928758},
{"learn":[0.6472424974],"iteration":35,"passed_time":2.124855758,"remaining_time":3.777521348},
{"learn":[0.6470839371],"iteration":36,"passed_time":2.178881815,"remaining_time":3.709987955},
{"learn":[0.6469768231],"iteration":37,"passed_time":2.247227354,"remaining_time":3.66652884},
{"learn":[0.6468363543],"iteration":38,"passed_time":2.302604316,"remaining_time":3.601509314},
{"learn":[0.6466474933],"iteration":39,"passed_time":2.364953131,"remaining_time":3.547429696},
{"learn":[0.6464676615],"iteration":40,"passed_time":2.422074525,"remaining_time":3.485424316},
{"learn":[0.6463528029],"iteration":41,"passed_time":2.475895756,"remaining_time":3.419094139},
{"learn":[0.646233849],"iteration":42,"passed_time":2.535064945,"remaining_time":3.360434927},
{"learn":[0.6461052855],"iteration":43,"passed_time":2.595577706,"remaining_time":3.303462535},
{"learn":[0.6460152468],"iteration":44,"passed_time":2.648144653,"remaining_time":3.236621243},
{"learn":[0.6459559837],"iteration":45,"passed_time":2.703180379,"remaining_time":3.173298705},
{"learn":[0.64576651],"iteration":46,"passed_time":2.75794474,"remaining_time":3.110022791},
{"learn":[0.6456500631],"iteration":47,"passed_time":2.815766106,"remaining_time":3.050413282},
{"learn":[0.6455625748],"iteration":48,"passed_time":2.879942308,"remaining_time":2.997490974},
{"learn":[0.6454596095],"iteration":49,"passed_time":2.933120898,"remaining_time":2.933120898},
{"learn":[0.6452355665],"iteration":50,"passed_time":2.996289722,"remaining_time":2.878788164},
{"learn":[0.6450759348],"iteration":51,"passed_time":3.049423897,"remaining_time":2.814852828},
{"learn":[0.6450004243],"iteration":52,"passed_time":3.103067968,"remaining_time":2.751777255},
{"learn":[0.6448990243],"iteration":53,"passed_time":3.156683124,"remaining_time":2.689026365},
{"learn":[0.6448048028],"iteration":54,"passed_time":3.211430569,"remaining_time":2.627534102},
{"learn":[0.6446669134],"iteration":55,"passed_time":3.26560012,"remaining_time":2.565828666},
{"learn":[0.6446127716],"iteration":56,"passed_time":3.315931029,"remaining_time":2.501491829},
{"learn":[0.6445666361],"iteration":57,"passed_time":3.366167192,"remaining_time":2.437569346},
{"learn":[0.6444379812],"iteration":58,"passed_time":3.429132566,"remaining_time":2.382956529},
{"learn":[0.644362527],"iteration":59,"passed_time":3.486547782,"remaining_time":2.324365188},
{"learn":[0.6442506572],"iteration":60,"passed_time":3.541968534,"remaining_time":2.26453726},
{"learn":[0.6441670417],"iteration":61,"passed_time":3.604212978,"remaining_time":2.209033761},
{"learn":[0.6441020859],"iteration":62,"passed_time":3.661915266,"remaining_time":2.150648648},
{"learn":[0.644053553],"iteration":63,"passed_time":3.715379136,"remaining_time":2.089900764},
{"learn":[0.6439251335],"iteration":64,"passed_time":3.788474615,"remaining_time":2.039947869},
{"learn":[0.6437910951],"iteration":65,"passed_time":3.84406261,"remaining_time":1.980274678},
{"learn":[0.6436853894],"iteration":66,"passed_time":3.904800321,"remaining_time":1.92325986},
{"learn":[0.6435841619],"iteration":67,"passed_time":3.960641682,"remaining_time":1.86383138},
{"learn":[0.6434954844],"iteration":68,"passed_time":4.01773266,"remaining_time":1.805068297},
{"learn":[0.6434451298],"iteration":69,"passed_time":4.067780622,"remaining_time":1.743334552},
{"learn":[0.6432684259],"iteration":70,"passed_time":4.120738554,"remaining_time":1.683118564},
{"learn":[0.6431806933],"iteration":71,"passed_time":4.174594575,"remaining_time":1.623453446},
{"learn":[0.6430824133],"iteration":72,"passed_time":4.228840832,"remaining_time":1.564091814},
{"learn":[0.6430081934],"iteration":73,"passed_time":4.286291213,"remaining_time":1.50599421},
{"learn":[0.642874721],"iteration":74,"passed_time":4.336523917,"remaining_time":1.445507972},
{"learn":[0.6427177515],"iteration":75,"passed_time":4.387979866,"remaining_time":1.385677852},
{"learn":[0.6426529174],"iteration":76,"passed_time":4.441093791,"remaining_time":1.326560483},
{"learn":[0.6425486429],"iteration":77,"passed_time":4.497231932,"remaining_time":1.268450032},
{"learn":[0.6424764153],"iteration":78,"passed_time":4.547953826,"remaining_time":1.208949751},
{"learn":[0.6423032312],"iteration":79,"passed_time":4.608152308,"remaining_time":1.152038077},
{"learn":[0.6421557734],"iteration":80,"passed_time":4.664048542,"remaining_time":1.094036078},
{"learn":[0.6420519823],"iteration":81,"passed_time":4.710229738,"remaining_time":1.033952869},
{"learn":[0.6419591527],"iteration":82,"passed_time":4.758822215,"remaining_time":0.974698526},
{"learn":[0.6418058149],"iteration":83,"passed_time":4.809614898,"remaining_time":0.9161171234},
{"learn":[0.6416733932],"iteration":84,"passed_time":4.862551289,"remaining_time":0.8580972862},
{"learn":[0.6416196311],"iteration":85,"passed_time":4.912459923,"remaining_time":0.7997027781},
{"learn":[0.6415249441],"iteration":86,"passed_time":4.960919488,"remaining_time":0.7412868201},
{"learn":[0.6414016732],"iteration":87,"passed_time":5.010294643,"remaining_time":0.6832219968},
{"learn":[0.641331561],"iteration":88,"passed_time":5.062604808,"remaining_time":0.625715201},
{"learn":[0.6412594955],"iteration":89,"passed_time":5.11291101,"remaining_time":0.5681012234},
{"learn":[0.6412252562],"iteration":90,"passed_time":5.161969094,"remaining_time":0.5105244159},
{"learn":[0.641127983],"iteration":91,"passed_time":5.211524284,"remaining_time":0.4531760247},
{"learn":[0.641038592],"iteration":92,"passed_time":5.26204381,"remaining_time":0.3960678137},
{"learn":[0.6409171821],"iteration":93,"passed_time":5.314220648,"remaining_time":0.3392055732},
{"learn":[0.6407988001],"iteration":94,"passed_time":5.367059375,"remaining_time":0.2824768092},
{"learn":[0.640733757],"iteration":95,"passed_time":5.417205334,"remaining_time":0.2257168889},
{"learn":[0.6406862452],"iteration":96,"passed_time":5.464455946,"remaining_time":0.1690037922},
{"learn":[0.640601351],"iteration":97,"passed_time":5.513526696,"remaining_time":0.112520953},
{"learn":[0.640434768],"iteration":98,"passed_time":5.560461947,"remaining_time":0.05616628229},
{"learn":[0.6402775062],"iteration":99,"passed_time":5.617537842,"remaining_time":0}
]}